netbox_more_metrics/__init__.py
netbox_more_metrics/api/__init__.py
netbox_more_metrics/api/serializers.py
netbox_more_metrics/api/urls.py
netbox_more_metrics/api/views.py
netbox_more_metrics/choices.py
netbox_more_metrics/collectors.py
netbox_more_metrics/fields.py
netbox_more_metrics/forms.py
netbox_more_metrics/metrics.py
netbox_more_metrics/migrations/0001_initial.py
netbox_more_metrics/migrations/0002_metric_metric_value.py
netbox_more_metrics/migrations/0003_alter_metric_content_type.py
netbox_more_metrics/migrations/0004_metric_label_renames.py
netbox_more_metrics/migrations/__init__.py
netbox_more_metrics/models.py
netbox_more_metrics/navigation.py
netbox_more_metrics/signals.py
netbox_more_metrics/tables.py
netbox_more_metrics/templates/netbox_more_metrics/metric.html
netbox_more_metrics/templates/netbox_more_metrics/metriccollection.html
netbox_more_metrics/urls.py
netbox_more_metrics/utilities.py
netbox_more_metrics/validators.py
netbox_more_metrics/views.py
netbox_more_metrics-0.3.2.dist-info/LICENSE
netbox_more_metrics-0.3.2.dist-info/METADATA
netbox_more_metrics-0.3.2.dist-info/WHEEL
netbox_more_metrics-0.3.2.dist-info/RECORD
