Metadata-Version: 2.1
Name: netbox-more-metrics
Version: 0.3.2
Summary: Provide customized metrics on data stored in NetBox.
Author: Daan van Gorkum
Author-email: me+netbox@dj.vg
Requires-Python: >=3.11,<4.0
Classifier: Programming Language :: Python :: 3
Classifier: Programming Language :: Python :: 3.11
Classifier: Programming Language :: Python :: 3.12
Classifier: Programming Language :: Python :: 3.13
Requires-Dist: prometheus-client (>=0.12.0)
